monito/__init__.py
monito/article.py
monito/gpe_mexico_ciudades.txt
monito/gpe_mexico_estados.txt
monito/gpe_mexico_municipios.txt
monito/gpe_world_capitals_es.txt
monito/gpe_world_cities_es.txt
monito/gpe_world_continents_es.txt
monito/gpe_world_countries_es.txt
monito/monito_main.py
monito/parsers.py
monito/tools.py
monito-0.1.0.dist-info/entry_points.txt
monito-0.1.0.dist-info/LICENSE
monito-0.1.0.dist-info/WHEEL
monito-0.1.0.dist-info/METADATA
monito-0.1.0.dist-info/RECORD
