Metadata-Version: 2.1
Name: monito
Version: 0.1.0
Summary: Tool to monitor and filter news websites and alike.
Home-page: https://gitlab.com/szs/monito/
License: MIT
Keywords: rss,rss feed,news feed,newsfeed
Author: Steffen Brinkmann
Author-email: s-b@mailbox.org
Requires-Python: >=3.9,<4.0
Classifier: Development Status :: 4 - Beta
Classifier: Intended Audience :: Information Technology
Classifier: License :: OSI Approved :: MIT License
Classifier: Programming Language :: Python :: 3
Classifier: Programming Language :: Python :: 3.10
Classifier: Programming Language :: Python :: 3.6
Classifier: Programming Language :: Python :: 3.7
Classifier: Programming Language :: Python :: 3.8
Classifier: Programming Language :: Python :: 3.9
Classifier: Topic :: Communications
Classifier: Topic :: Education
Classifier: Topic :: Internet :: WWW/HTTP :: Dynamic Content :: News/Diary
Classifier: Topic :: Utilities
Requires-Dist: alive-progress (>=2.1.0,<3.0.0)
Requires-Dist: bs4 (>=0.0.1,<0.0.2)
Requires-Dist: feedparser (>=6.0.8,<7.0.0)
Requires-Dist: lxml (>=4.7.1,<5.0.0)
Requires-Dist: requests (>=2.26.0,<3.0.0)
Requires-Dist: selenium (>=4.1.0,<5.0.0)
Requires-Dist: spacy (>=3.2.1,<4.0.0)
Requires-Dist: spacy-syllables (>=3.0.1,<4.0.0)
Requires-Dist: toml (>=0.10.2,<0.11.0)
Project-URL: Documentation, https://monito.readthedocs.io/en/latest/
Project-URL: Repository, https://gitlab.com/szs/monito/
